ps3838api/__init__.py
ps3838api/matching.py
ps3838api/py.typed
ps3838api/tank.py
ps3838api/totals.py
ps3838api/api/__init__.py
ps3838api/api/client.py
ps3838api/api/default_client.py
ps3838api/api/v4client.py
ps3838api/models/__init__.py
ps3838api/models/bets.py
ps3838api/models/client.py
ps3838api/models/errors.py
ps3838api/models/event.py
ps3838api/models/fixtures.py
ps3838api/models/lines.py
ps3838api/models/odds.py
ps3838api/models/sports.py
ps3838api/models/tank.py
ps3838api/utils/match_leagues.py
ps3838api/utils/ops.py
ps3838api-1.2.0.dist-info/licenses/LICENSE
ps3838api-1.2.0.dist-info/METADATA
ps3838api-1.2.0.dist-info/WHEEL
ps3838api-1.2.0.dist-info/top_level.txt
ps3838api-1.2.0.dist-info/RECORD
