Metadata-Version: 2.4
Name: ps3838api
Version: 1.2.0
Summary: A lightweight Python library to interact with the Pinnacle API (PS3838, Pinnacle888 etc.) and place bets.
Author-email: Ilias Dzhabbarov <ilias.dzabbarov@gmail.com>
License: MIT
Project-URL: Homepage, https://github.com/iliyasone/ps3838api
Project-URL: Issues, https://github.com/iliyasone/ps3838api/issues
Keywords: ps3838,sports betting,api,pinnacle,odds,python
Classifier: Programming Language :: Python :: 3
Classifier: License :: OSI Approved :: MIT License
Classifier: Operating System :: OS Independent
Requires-Python: >=3.12
License-File: LICENSE
Requires-Dist: rapidfuzz>=3.14.3
Requires-Dist: requests>=2.32.5
Dynamic: license-file
